{
  "personal": {
    "name": "andyechc",
    "title": "Desarrollador de Software",
    "description": "Coding for fun and profit",
    "email": "andyechc@gmail.com",
    "location": "La Habana, Cuba",
    "avatar": "/profile.png",
    "social": {
      "github": "https://github.com/andyechc",
      "linkedin": "https://linkedin.com/in/andyechc",
      "twitter": "https://x.com/andyechc",
      "substack": "https://substack.com/@andyechc"
    }
  },
  "about": {
    "title": "Sobre Mí",
    "description": "Soy un desarrollador de software especializado en crear aplicaciones modernas y eficientes. Me enfoco en minimalismo y funcionalidad para ofrecer la mejor experiencia de usuario.",
    "highlights": [
      "Desarrollo frontend con tecnologías modernas",
      "Diseño minimalista y enfoque en UX",
      "+4 años de experiencia",
      "Aprendizaje continuo y adaptación"
    ]
  },
  "technologies": {
    "title": "Tecnologías",
    "categories": [
      {
        "name": "Frontend",
        "items": [
          { "name": "React", "icon": "react" },
          { "name": "TypeScript", "icon": "typescript" },
          { "name": "Tailwind CSS", "icon": "tailwind" },
          { "name": "Astro", "icon": "astro" }
        ]
      },
      {
        "name": "Backend",
        "items": [
          { "name": "Ktor", "icon": "ktor" },
          { "name": "Node.js", "icon": "nodejs" },
          { "name": "Python", "icon": "python" },
          { "name": "MongoDB", "icon": "mongodb" }
        ]
      },
      {
        "name": "Nativo",
        "items": [
          { "name": "Kotlin", "icon": "kotlin" },
          { "name": "Swift", "icon": "swift" },
          { "name": "KMP", "icon": "kmp" }
        ]
      },
      {
        "name": "Herramientas",
        "items": [
          { "name": "Git", "icon": "git" }
        ]
      }
    ]
  },
  "projects": [
    {
      "id": 1,
      "title": "Isla Pos",
      "description": "App de pago con diferentes métodos (contactless, payment link) para terminales POS iMin",
      "image": "/projects/islapos.png",
      "technologies": ["Kotlin", "Android"],
      "liveUrl": "",
      "githubUrl": "",
      "featured": true,
      "private": true,
      "noCode": true
    },
    {
      "id": 2,
      "title": "entreGo!",
      "description": "App delivery-boy con sistema de gestión de ordenes de entrega y almacenamiento local de ordenes completadas en caso de pérdida de conexión u otros problemas.",
      "image": "/projects/entrego.png",
      "technologies": ["KMP", "Android", "iOS"],
      "liveUrl": "",
      "githubUrl": "",
      "featured": true,
      "private": true,
      "noCode": true
    },
    {
      "id": 3,
      "title": "Marky",
      "description": "Un editor de markdown en línea con almacenamiento local y exportación de archivo.",
      "image": "/projects/marky.png",
      "technologies": ["reactjs", "tailwindcss"],
      "liveUrl": "https://marky-md.vercel.app",
      "githubUrl": "https://github.com/andyechc/marky.git",
      "featured": true,
      "private": false,
      "noPreview": false
    }
  ],
  "experience": {
    "title": "Experiencia",
    "items": [
      {
        "id": 1,
        "company": "Tech Company",
        "position": "Desarrollador Frontend",
        "period": "2022 - Presente",
        "description": "Desarrollo de aplicaciones web modernas con React y TypeScript. Enfoque en optimización de rendimiento y experiencia de usuario.",
        "technologies": ["React", "TypeScript", "Tailwind CSS", "GraphQL"]
      },
      {
        "id": 2,
        "company": "Startup Digital",
        "position": "Desarrollador Full Stack",
        "period": "2020 - 2022",
        "description": "Creación de aplicaciones web completas desde el diseño hasta el despliegue. Implementación de APIs RESTful y bases de datos.",
        "technologies": ["Node.js", "React", "MongoDB", "Docker"]
      },
      {
        "id": 3,
        "company": "Agencia de Software",
        "position": "Desarrollador Junior",
        "period": "2019 - 2020",
        "description": "Desarrollo de sitios web y aplicaciones para clientes diversos. Aprendizaje de mejores prácticas y metodologías ágiles.",
        "technologies": ["HTML", "CSS", "JavaScript", "WordPress"]
      }
    ]
  },
  "contact": {
    "title": "Contacto",
    "description": "¿Interesado en colaborar? No dudes en contactarme.",
    "form": {
      "name": "Nombre",
      "email": "Email",
      "message": "Mensaje",
      "submit": "Enviar Mensaje"
    }
  },
  "seo": {
    "title": "J. Andy Echavarria Contreras - Desarrollador de Software",
    "description": "Portafolio de J. Andy Echavarria Contreras, desarrollador de software especializado en crear experiencias modernas y eficientes.",
    "keywords": ["desarrollador de software", "kotlin", "frontend", "react", "typescript", "minimalista"],
    "image": "/og-image.jpg"
  }
}
